LICENSE
README.md
setup.cfg
setup.py
bin/oblivious-robots
bin/oblivious-robots.bat
src/oblivious_robots_target_searching/__init__.py
src/oblivious_robots_target_searching/__main__.py
src/oblivious_robots_target_searching/_terminal.py
src/oblivious_robots_target_searching/_version.py
src/oblivious_robots_target_searching.egg-info/PKG-INFO
src/oblivious_robots_target_searching.egg-info/SOURCES.txt
src/oblivious_robots_target_searching.egg-info/dependency_links.txt
src/oblivious_robots_target_searching.egg-info/requires.txt
src/oblivious_robots_target_searching.egg-info/top_level.txt
src/oblivious_robots_target_searching/Algorithm/__init__.py
src/oblivious_robots_target_searching/Algorithm/main.py
src/oblivious_robots_target_searching/Graph/__init__.py
src/oblivious_robots_target_searching/Graph/chordAdder.py
src/oblivious_robots_target_searching/Graph/main.py
src/oblivious_robots_target_searching/Robot/__init__.py
src/oblivious_robots_target_searching/Robot/main.py