Metadata-Version: 2.1
Name: oblivious-robots-target-searching
Version: 0.1.3
Summary: This package provides a powerful Playground for designing and testing algorithms for oblivious robots
Home-page: https://github.com/Sairyo-No-Developers/oblivious-robots-target-search
Author: Sairyö No Developers
Author-email: tech@sairyonodevs.in
License: MIT
Keywords: oblivious robots target searching graph
Platform: UNKNOWN
License-File: LICENSE
